[
    {
        "mail": "santi.delga02@gmail.com",
        "password": "tukituki02",
        "name": "Santiago Delgado",
        "phoneNumber": "2235555555",
        "birthdate": "2002-09-15",
        "adress": "Florisbelo Acosta 3982, Mar del Plata",
        "dogs": null,
        "rating": 0,
        "fechaInicio": "2022-09-28",
        "fechaFin": "2022-10-27",
        "saldo": 0,
        "tamanio": "pequenio-mediano",
        "direccionCuidado": "Florisbelo",
        "descripcion": "elV"
    },
    {
        "mail": "s@.com",
        "password": "123",
        "name": "jorge",
        "phoneNumber": "238472",
        "birthdate": "2000-09-18",
        "adress": "mi casa",
        "dogs": null,
        "rating": 0,
        "fechaInicio": "2022-10-20",
        "fechaFin": "2022-11-24",
        "saldo": 0,
        "tamanio": "pequenio-mediano-grande",
        "direccionCuidado": "Miami",
        "descripcion": "Soy muy buen cuidador"
    },
    {
        "mail": "santidistefano12@gmail.com",
        "password": "contrasenia",
        "name": "Santiago Distefano",
        "phoneNumber": "223594857649",
        "birthdate": "2000-02-01",
        "adress": "daireaux",
        "dogs": null,
        "rating": 0,
        "fechaInicio": "2022-10-20",
        "fechaFin": "2022-10-26",
        "saldo": 0,
        "tamanio": "pequenio-mediano-grande",
        "direccionCuidado": "Daireaux",
        "descripcion": "Soy un heroe"
    },
    {
        "mail": "test@gmail.com",
        "password": "123456",
        "name": "Pepe Argento",
        "phoneNumber": "2235768904",
        "birthdate": "2013-06-13",
        "adress": "Mi casa 1231, ciudad",
        "dogs": null,
        "rating": 0,
        "fechaInicio": "2022-10-27",
        "fechaFin": "2022-11-10",
        "saldo": 0,
        "tamanio": "pequenio-mediano",
        "direccionCuidado": "Mi casa",
        "descripcion": "Probando"
    }
]